mdbpg/__init__.py
mdbpg/mongodb.py
mdbpg/postgres.py
mdbpg-0.2.1.dist-info/LICENSE
mdbpg-0.2.1.dist-info/METADATA
mdbpg-0.2.1.dist-info/WHEEL
mdbpg-0.2.1.dist-info/top_level.txt
mdbpg-0.2.1.dist-info/RECORD
