Metadata-Version: 2.1
Name: mdbpg
Version: 0.2.1
Summary: Handle both Postgres and MongoDB queries in an interchangable manner.
Home-page: https://github.com/wuotes/mdbpg
Author: Jordan Schaffrin
Author-email: mailbox@xrtuen.com
License: Mozilla Public License 2.0
Download-URL: https://pypi.org/project/mdbpg/
Platform: UNKNOWN
Classifier: License :: OSI Approved :: Mozilla Public License 2.0 (MPL 2.0)
Classifier: Programming Language :: Python :: 3.9
Classifier: Programming Language :: Python :: 3.10
Classifier: Programming Language :: Python :: 3.11
Classifier: Programming Language :: Python :: 3.12
Classifier: Operating System :: Microsoft :: Windows
Classifier: Operating System :: POSIX :: Linux
Classifier: Operating System :: MacOS
Requires-Python: >=3.9
License-File: LICENSE
Requires-Dist: mtoml (>=1.2.0)
Requires-Dist: psycopg2 (>=2.9.3)
Requires-Dist: pymongo (>=4.1.1)
Requires-Dist: dnspython (>=2.2.1)
